{
	"stanzas":3,
	"music": [
	],
	"lyrics": [
		{"label":"1",
			"lines":[
				"Passant, si tard que veux-tu?",
				"Qui donc ici cherches-tu?",
				"Pourquoi, voyageur étrange,",
				"À ma porte es-tu venu?",
				"N'es-tu pas quelque saint ange",
				"Sur la terre descendu?"
			]
		},
		{"label":"2",
			"lines":[
				"C'est moi, c'est moi, ton Sauveur!",
				"Je veux entrer dans ton coeur.",
				"Pourquoi me laisser attendre?",
				"Ouvre, c'est un bienfaiteur,",
				"Qui chez toi s'offre à répandre",
				"Tous les trésors du bonheur."
			]
		},
		{"label":"3",
			"lines":[
				"Vraiment!  Vraiment!  C'est sa voix;",
				"C'est lui!  C'est lui!  Je le vois.",
				"Oh!  Ta grâce est la plus forte,",
				"Mon Sauveur, je te reçois.",
				"Je ne puis fermer la porte,",
				"Quand tu me montres ta croix."
			]
		}
	]
}

